[
    {
        "patientName": "João Silva",
        "phone": "(11) 98765-4321",
        "insurance": "Unimed",
        "date": "2024-12-15",
        "time": "14:00",
        "doctor": "Dr. Pedro Almeida"
    },
    {
        "patientName": "Maria Oliveira",
        "phone": "(21) 91234-5678",
        "insurance": "Particular",
        "date": "2024-12-16",
        "time": "09:30",
        "doctor": "Dra. Fernanda Costa"
    },
    {
        "patientName": "Carlos Pereira",
        "phone": "(31) 97654-3210",
        "insurance": "Amil",
        "date": "2024-12-17",
        "time": "11:00",
        "doctor": "Dr. Ricardo Mendes"
    },
    {
        "patientName": "Ana Souza",
        "phone": "(41) 98765-1234",
        "insurance": "Outros",
        "date": "2024-12-18",
        "time": "15:00",
        "doctor": "Dra. Camila Rocha"
    },
    {
        "patientName": "Luiz Fernando",
        "phone": "(51) 92345-6789",
        "insurance": "Unimed",
        "date": "2024-12-19",
        "time": "10:00",
        "doctor": "Dr. Marcelo Teixeira"
    }
]